mpsp/__init__.py
mpsp/base_socket/__init__.py
mpsp/mps/__init__.py
mpsp-0.0.2.dist-info/METADATA
mpsp-0.0.2.dist-info/WHEEL
mpsp-0.0.2.dist-info/licenses/LICENSE
mpsp-0.0.2.dist-info/RECORD
