Metadata-Version: 2.1
Name: mpsp
Version: 0.0.2
Summary: mpsp protocol
Project-URL: Homepage, https://github.com/smlp6d/mpsp
Project-URL: Bug Tracker, https://github.com/smlp6d/mpsp/issues
Author-email: std46d6b <dev@m5k.ru>
License-File: LICENSE
Classifier: License :: OSI Approved :: MIT License
Classifier: Operating System :: OS Independent
Classifier: Programming Language :: Python :: 3
Requires-Python: >=3.7
